LICENSE
pathlib_tree/__init__.py
pathlib_tree/exceptions.py
pathlib_tree/patterns.py
pathlib_tree/tree.py
pathlib_tree/utils.py
pathlib_tree-2.4.9.dist-info/LICENSE
pathlib_tree-2.4.9.dist-info/METADATA
pathlib_tree-2.4.9.dist-info/WHEEL
pathlib_tree-2.4.9.dist-info/RECORD
